pydarwin/ChromosomeSpecifications.py
pydarwin/GA.py
pydarwin/__init__.py
tests/ChromosomeSpecifications_test.py
tests/GA_test.py
tests/__init__.py
pydarwin-0.0.4.dist-info/METADATA
pydarwin-0.0.4.dist-info/WHEEL
pydarwin-0.0.4.dist-info/top_level.txt
pydarwin-0.0.4.dist-info/RECORD
